seqalign/__init__.py
seqalign/atac_seq.py
seqalign/chip_seq.py
seqalign/doc.py
seqalign/seqalign.py
seqalign-0.1.15.dist-info/LICENSE
seqalign-0.1.15.dist-info/METADATA
seqalign-0.1.15.dist-info/WHEEL
seqalign-0.1.15.dist-info/entry_points.txt
seqalign-0.1.15.dist-info/top_level.txt
seqalign-0.1.15.dist-info/RECORD
