Metadata-Version: 2.1
Name: seqalign
Version: 0.1.15
Summary: Manage sequence alignments
Home-page: https://github.com/anthony-aylward/seqalign
Author: Anthony Aylward
Author-email: aaylward@salk.edu
License: UNKNOWN
Platform: UNKNOWN
Classifier: Programming Language :: Python :: 3
Classifier: License :: OSI Approved :: MIT License
Classifier: Operating System :: OS Independent
License-File: LICENSE
Requires-Dist: biopython
Requires-Dist: pyhg19
Requires-Dist: tempfifo
Requires-Dist: cutadapt
Requires-Dist: picardtools
